{"QueryScripts":[{"Name":"foofewf","ScriptText":"foofeyfoof","TranslatedScript":"foofeyfoof","RunOnParentRowSelect":false,"ResultDataTable":null,"ResultText":null,"StartTime":"0001-01-01T00:00:00","EndTime":"0001-01-01T00:00:00","Duration":"00:00:00","TaskStatus":0},{"Name":"barasdf","ScriptText":"barasdfadsfasdf","TranslatedScript":"barasdfadsfasdf","RunOnParentRowSelect":false,"ResultDataTable":null,"ResultText":null,"StartTime":"0001-01-01T00:00:00","EndTime":"0001-01-01T00:00:00","Duration":"00:00:00","TaskStatus":0},{"Name":"goo","ScriptText":"goo gooo gooooooooo","TranslatedScript":"goo gooo gooooooooo","RunOnParentRowSelect":false,"ResultDataTable":null,"ResultText":null,"StartTime":"0001-01-01T00:00:00","EndTime":"0001-01-01T00:00:00","Duration":"00:00:00","TaskStatus":0},{"Name":"gar","ScriptText":"garyeasdef gar gar","TranslatedScript":"garyeasdef gar gar","RunOnParentRowSelect":false,"ResultDataTable":null,"ResultText":null,"StartTime":"0001-01-01T00:00:00","EndTime":"0001-01-01T00:00:00","Duration":"00:00:00","TaskStatus":0}],"LibraryScripts":{},"Variables":{},"Settings":{"QueryScriptFont":"Consolas, 15.75pt","ResultTableFont":"Cooper Black, 15.75pt","TextResultsFont":"Copperplate Gothic Light, 15.75pt"}}